high_error_rate/high_error_rate.py
high_error_rate/high_error_rate.rego
high_error_rate/manifest.toml
high_error_rate/test_high_error_rate.py
inactive_load_balancers/inactive_load_balancers.py
inactive_load_balancers/inactive_load_balancers.rego
inactive_load_balancers/manifest.toml
inactive_load_balancers/test_inactive_load_balancers.py
inactive_load_balancers/inactive_load_balancers/inactive_load_balancers.py
low_request_counts/low_request_count.py
low_request_counts/low_request_count.rego
low_request_counts/manifest.toml
low_request_counts/test_low_request_count.py
no_healthy_targets/manifest.toml
no_healthy_targets/no_healthy_targets.py
no_healthy_targets/no_healthy_targets.rego
no_healthy_targets/test_no_healthy_targets.py
opsbox_elb_checks-0.2.1.dist-info/licenses/LICENCE.txt
opsbox_elb_checks-0.2.1.dist-info/METADATA
opsbox_elb_checks-0.2.1.dist-info/WHEEL
opsbox_elb_checks-0.2.1.dist-info/entry_points.txt
opsbox_elb_checks-0.2.1.dist-info/top_level.txt
opsbox_elb_checks-0.2.1.dist-info/RECORD
