Metadata-Version: 2.4
Name: opsbox-elb-checks
Version: 0.2.1
Summary: Collection of ELB checks for opsbox
License: Mozilla Public License Version 2.0
Requires-Python: ==3.11.*
License-File: LICENCE.txt
Requires-Dist: opsbox-elb-provider>=0.1.3
Requires-Dist: opsbox-rego-handler>=0.2.0
Dynamic: license-file
